cohmetrixBR/__init__.py
cohmetrixBR/utils.py
cohmetrixBR/features/__init__.py
cohmetrixBR/features/connectives.py
cohmetrixBR/features/descriptive.py
cohmetrixBR/features/lexical_diversity_coh.py
cohmetrixBR/features/readability.py
cohmetrixBR/features/referential_cohesion.py
cohmetrixBR/features/situation_model.py
cohmetrixBR/features/syntactic_complexity.py
cohmetrixBR/features/syntactic_pattern_density.py
cohmetrixBR/features/word_information.py
cohmetrixBR/resources/MRC.csv
cohmetrixBR/resources/__init__.py
cohmetrixBR/resources/intentional_verbs.csv
cohmetrixBR/resources/layout-one.txt
cohmetrix_br_lib-0.1.5.dist-info/licenses/LICENSE
cohmetrix_br_lib-0.1.5.dist-info/METADATA
cohmetrix_br_lib-0.1.5.dist-info/WHEEL
cohmetrix_br_lib-0.1.5.dist-info/top_level.txt
cohmetrix_br_lib-0.1.5.dist-info/RECORD
