Metadata-Version: 2.4
Name: cohmetrix-br-lib
Version: 0.1.5
Summary: Biblioteca para extração de características linguísticas para o Português Brasileiro.
Project-URL: Github, https://github.com/moesio-f/cohmetrix-br
Classifier: Development Status :: 3 - Alpha
Classifier: Programming Language :: Python :: 3.8
Classifier: Programming Language :: Python :: 3.9
Classifier: Programming Language :: Python :: 3.10
Requires-Python: >=3.10
License-File: LICENSE
Requires-Dist: nltk>=3.8.1
Requires-Dist: numpy>=1.21.0
Requires-Dist: pandas>=2.0.0
Requires-Dist: pyphen>=0.14.0
Requires-Dist: spacy>=3.6.0
Requires-Dist: unidecode>=1.3.7
Requires-Dist: tqdm>=4.65.0
Requires-Dist: pip>=25.2
Requires-Dist: gensim>=4.3.3
Requires-Dist: lexical-diversity>=0.1.1
Dynamic: license-file
